{
  "$schema": "https://json-schema.org/draft/2020-12/schema",
  "$id": "https://911bench.ece.ubc.ca/schemas/action_registry.schema.json",
  "title": "ActionClassRegistry",
  "description": "Defines the catalog of action classes with payload schemas, evidence requirements, and risk metadata. Architecture Document Section 3.4.1.",
  "type": "object",
  "required": ["action_classes"],
  "properties": {
    "action_classes": {
      "type": "array",
      "minItems": 1,
      "items": {
        "type": "object",
        "required": ["name", "description", "payload_schema", "required_evidence", "risk_level", "cad_fields_written", "freshness_strategy"],
        "properties": {
          "name": { "type": "string", "description": "Unique action class identifier (e.g., 'cad_update.address')." },
          "description": { "type": "string" },
          "payload_schema": {
            "type": "object",
            "description": "JSON Schema for the proposed_payload in ActionProposals of this class."
          },
          "required_evidence": {
            "type": "array",
            "items": {
              "type": "string",
              "enum": ["human_communication", "operational_record", "procedural_reference", "sensor_or_signal", "external_source"],
              "description": "Abstract evidence categories required for proposals of this class."
            }
          },
          "risk_level": {
            "type": "string",
            "enum": ["high", "medium", "low"]
          },
          "cad_fields_written": {
            "type": "array",
            "items": { "type": "string" },
            "description": "CAD fields that this action class writes. Empty for read-only actions."
          },
          "critical_fields": {
            "type": "array",
            "items": { "type": "string" },
            "description": "Fields where low confidence triggers the uncertainty_critical_field predicate."
          },
          "freshness_strategy": {
            "type": "string",
            "enum": ["occ", "lease", "none"],
            "description": "Data freshness enforcement mechanism. Not a governance operator; implementation mechanism for Bound on data currency."
          },
          "rollback_semantics": {
            "type": ["object", "null"],
            "description": "If the action is reversible, defines how. Required for A >= A3 unless Checkpoint is present (Obligation 2).",
            "properties": {
              "reversible": { "type": "boolean" },
              "rollback_mechanism": { "type": "string" },
              "rollback_window_ms": { "type": "integer" }
            }
          }
        }
      }
    }
  }
}
